{
  "ticker": "NIFTYBEES.NS",
  "market_cap": 524917704188.60144,
  "eps": 207.67516879101865,
  "revenue": 159563897710.4379,
  "revenue_growth": -0.01821994640330271,
  "debt_to_equity": 0.8122286518993542,
  "operating_cash_flow": 33561507678.519524,
  "free_cash_flow": 16454683143.04341,
  "operating_margin": 0.19072085607166436,
  "roe": 0.21762378539500637,
  "sector": "Financials",
  "industry": "Diversified",
  "pe_ratio": 10.856730451012597,
  "current_price": null,
  "source": "synthetic"
}